envi2numpy.cpython-36m-x86_64-linux-gnu.so
envi2numpy-1.4.dist-info/LICENSE
envi2numpy-1.4.dist-info/RECORD
envi2numpy-1.4.dist-info/WHEEL
envi2numpy-1.4.dist-info/top_level.txt
envi2numpy-1.4.dist-info/METADATA
