Metadata-Version: 2.1
Name: envi2numpy
Version: 1.4
Summary: Package used for reading and converting hyperspectral ENVI captures to numpy
Home-page: https://github.com/ArendJanKramer/envi2numpy
Author: Arend Jan Kramer
Author-email: github@arendjan.eu
License: gpl-2.0
Platform: UNKNOWN
